aci/__init__.py
aci/_client.py
aci/_constants.py
aci/_exceptions.py
aci/libs/__init__.py
aci/libs/_compatible_schema.py
aci/libs/_function_schema.py
aci/libs/_tool.py
aci/meta_functions/__init__.py
aci/meta_functions/_aci_execute_function.py
aci/meta_functions/_aci_get_function_definition.py
aci/meta_functions/_aci_search_apps.py
aci/meta_functions/_aci_search_functions.py
aci/meta_functions/_aci_search_functions_with_intent.py
aci/resource/__init__.py
aci/resource/_base.py
aci/resource/app_configurations.py
aci/resource/apps.py
aci/resource/functions.py
aci/types/__init__.py
aci/types/app_configurations.py
aci/types/apps.py
aci/types/enums.py
aci/types/functions.py
aci/utils/__init__.py
aci/utils/_logging.py
aci/utils/_type_check.py
acicli-0.0.2b1.dist-info/METADATA
acicli-0.0.2b1.dist-info/WHEEL
acicli-0.0.2b1.dist-info/RECORD
