Metadata-Version: 2.4
Name: acicli
Version: 0.0.2b1
Summary: Add your description here
Author-email: Aipolabs <support@aipolabs.xyz>
Maintainer-email: Aipolabs <support@aipolabs.xyz>
Keywords: ACI,API,Agent Computer Interface,Aipolabs,Aipotheosis Labs,Function Calling,LLM,MCP,Tool Calling
Classifier: Development Status :: 4 - Beta
Classifier: Intended Audience :: Developers
Classifier: Operating System :: MacOS
Classifier: Operating System :: Microsoft :: Windows
Classifier: Operating System :: OS Independent
Classifier: Operating System :: POSIX
Classifier: Operating System :: POSIX :: Linux
Classifier: Programming Language :: Python :: 3.10
Classifier: Programming Language :: Python :: 3.11
Classifier: Programming Language :: Python :: 3.12
Classifier: Programming Language :: Python :: 3.13
Classifier: Topic :: Software Development :: Libraries :: Python Modules
Classifier: Typing :: Typed
Requires-Python: >=3.10
Requires-Dist: griffe>=1.7.2
Requires-Dist: httpx>=0.28.1
Requires-Dist: pydantic>=2.11.3
Requires-Dist: tenacity>=9.1.2
Requires-Dist: typing-extensions>=4.13.2
